redis_gt/__init__.py
redis_gt/async_throttle.py
redis_gt/decorators.py
redis_gt/defaults.py
redis_gt/exceptions.py
redis_gt/throttle.py
redis_gt-1.2.0.dist-info/LICENSE
redis_gt-1.2.0.dist-info/METADATA
redis_gt-1.2.0.dist-info/WHEEL
redis_gt-1.2.0.dist-info/top_level.txt
redis_gt-1.2.0.dist-info/RECORD
