Metadata-Version: 2.1
Name: redis-gt
Version: 1.2.0
Summary: Global throttling with Redis.
Home-page: https://github.com/sukobuto/python-redis-gt
Author: sukobuto
Author-email: sukobuto@gmail.com
License: MIT
Keywords: throttle redis async
Platform: UNKNOWN
Classifier: Programming Language :: Python :: 3.6
Classifier: Programming Language :: Python :: 3.7
Requires-Dist: redis (==2.10.6)
